[
  {
    "slug": "bangladesh-protest-archive-official-launch",
    "title": "Bangladesh Protest Archive: Official Launch",
    "url": "https://www.facebook.com/share/p/17wDRGT9Nu/",
    "date": "2025-12-01T12:00:00.000Z"
  },
  {
    "slug": "engagemedia-tech-tales-youth-film-screening-dhaka",
    "title": "EngageMedia’s Tech Tales Youth Film Screening Premieres in Dhaka",
    "url": "https://www.facebook.com/share/p/1J5D4C7zVb/",
    "date": "2025-11-28T12:00:00.000Z"
  },
  {
    "slug": "localization-sprint-2025",
    "title": "Localization Sprint 2025",
    "url": "https://www.facebook.com/share/p/1CQgT6JfVX/",
    "date": "2025-11-25T12:00:00.000Z"
  },
  {
    "slug": "open-tech-camp-2025-penang-engagemedia",
    "title": "Open Tech Camp 2025 in Penang, Malaysia, organized by EngageMedia",
    "url": "https://www.facebook.com/share/p/1HMZNUrrCh/",
    "date": "2025-11-22T12:00:00.000Z"
  },
  {
    "slug": "decolonizing-shutdown-circumvention-rightscon",
    "title": "Learning session titled “Decolonizing Shutdown Circumvention: Strategy and Skill for Circumvention Training in Shutdown Areas” at Rightscon",
    "url": "https://www.facebook.com/share/p/17pp94ZAEJ/",
    "date": "2025-11-19T12:00:00.000Z"
  },
  {
    "slug": "bpa-meeting-un-secretary-general",
    "title": "Bangladesh Protest Archive (BPA) participated in a meeting with the Secretary-General of the United Nations",
    "url": "https://www.facebook.com/activate.rights/posts/pfbid0NjsJ3vwwcbYuYwSePrffvPxRkVek9vERNB5xxtH1SvWWMBgJjKqT4bvWe1atxYX4l",
    "date": "2025-11-16T12:00:00.000Z"
  },
  {
    "slug": "meeting-anfrel-activate-rights",
    "title": "Meeting between ANFREL and Activate Rights",
    "url": "https://www.facebook.com/share/p/1dcC9kwWUv/",
    "date": "2025-11-13T12:00:00.000Z"
  },
  {
    "slug": "human-rights-game-based-learning-mekateam",
    "title": "Session on human rights using a game-based learning approach with Mekateam",
    "url": "https://www.facebook.com/share/p/1D6KiDkf5B/",
    "date": "2025-11-10T12:00:00.000Z"
  },
  {
    "slug": "andolon-mixtape",
    "title": "Andolon Mixtape",
    "url": "https://activaterights.org/andolonmixtape/",
    "date": "2025-11-07T12:00:00.000Z"
  },
  {
    "slug": "co-learning-digital-rights-lal-sobuj-society",
    "title": "Co-Learning Workshop on Digital Rights and Democratic Participation for Youth, with partner Lal Sobuj Society",
    "url": "https://www.facebook.com/share/p/1BxoXEtuBq/",
    "date": "2025-11-04T12:00:00.000Z"
  },
  {
    "slug": "co-learning-digital-rights-skillup-daffodil",
    "title": "Co-Learning Workshop on Digital Rights & Democratic Participation for Youth, hosted in partnership with SkillUp Club, HRDI & Daffodil International University at Daffodil Smart City",
    "url": "https://www.facebook.com/share/p/1AMgCrFoJu/",
    "date": "2025-11-01T12:00:00.000Z"
  },
  {
    "slug": "open-tech-camp-kuala-lumpur-2025",
    "title": "Open Tech Camp Kuala Lumpur 2025",
    "url": "https://www.facebook.com/share/p/1HHytUzPG5/",
    "date": "2025-10-29T12:00:00.000Z"
  },
  {
    "slug": "asia-pacific-digital-rights-assembly-kuala-lumpur-2025",
    "title": "Asia-Pacific Digital Rights Assembly 2025 in Kuala Lumpur",
    "url": "https://youthdemocracycohort.com/stories/gen-d-defending-digital-rights-for-the-next-generations-democratic-future-project/",
    "date": "2025-10-26T12:00:00.000Z"
  },
  {
    "slug": "internet-freedom-campaigner-2025",
    "title": "Internet Freedom Campaigner 2025",
    "url": "https://www.facebook.com/share/p/14TD25ENa84/",
    "date": "2025-10-23T12:00:00.000Z"
  },
  {
    "slug": "archive-resist-workshop-archiving-violations",
    "title": "Archive & Resist (Workshop on archiving human rights violations)",
    "url": "https://www.facebook.com/share/p/1AeUxvjBc2/",
    "date": "2025-10-20T12:00:00.000Z"
  },
  {
    "slug": "asian-fact-checkers-network-conference-singapore-2025",
    "title": "Asian Fact-Checkers Network Conference 2025 in Singapore",
    "url": "https://www.facebook.com/share/p/14PkH7Xf6jT/",
    "date": "2025-10-17T12:00:00.000Z"
  },
  {
    "slug": "activate-rights-forum-information-democracy-coalition",
    "title": "Activate Rights has joined the civil society coalition of Forum on Information and Democracy",
    "url": "https://www.facebook.com/activate.rights/posts/pfbid0Pjy78z79Luuoso2TRoY19m5sgFNBS3MDD2cC6nk7oZCvcBLrWKWUvkkuynWHiciFl",
    "date": "2025-10-14T12:00:00.000Z"
  },
  {
    "slug": "iffat-nowshin-clic-act-podcast-youth-women-rising",
    "title": "Iffat Nowshin Joye, representing Activate Rights, took part in the Clic Act podcast: “Youth Movement and Women Rising: Social Media Activism for Democracy in Indonesia and Bangladesh”",
    "url": "https://www.youtube.com/watch?v=ZoAeFNA4nn0",
    "date": "2025-10-11T12:00:00.000Z"
  },
  {
    "slug": "co-learning-digital-rights-forensiq-ula",
    "title": "Co-Learning Workshop on Digital Rights & Democratic Participation for Youth, hosted in partnership with ForensIQ & University of Liberal Arts",
    "url": "https://www.facebook.com/share/p/1CKqxAMSGk/",
    "date": "2025-10-08T12:00:00.000Z"
  },
  {
    "slug": "civic-tech-bootcamp-2025",
    "title": "Civic Tech Bootcamp 2025",
    "url": "https://www.facebook.com/share/p/1BvpZZZQCc/",
    "date": "2025-10-05T12:00:00.000Z"
  },
  {
    "slug": "co-learning-digital-rights-democratic-participation-youth",
    "title": "Co-Learning Workshop on Digital Rights & Democratic Participation for Youth",
    "url": "https://www.facebook.com/share/p/1GDktReWY4/",
    "date": "2025-10-02T12:00:00.000Z"
  },
  {
    "slug": "civil-society-week-2025",
    "title": "Civil Society Week 2025",
    "url": "https://www.facebook.com/share/p/17xHnhqNj4/",
    "date": "2025-09-29T12:00:00.000Z"
  },
  {
    "slug": "open-tech-camp-notes-engagemedia-2025",
    "title": "Open Tech Camp — notes from Kuala Lumpur 2025 (EngageMedia)",
    "url": "https://engagemedia.org/2025/notes-from-the-open-tech-camp-kuala-lumpur-2025-from-ideas-to-action-open-tech-for-all/",
    "date": "2025-09-26T12:00:00.000Z"
  },
  {
    "slug": "beyond-fake-news-fimi-briefing-journalists",
    "title": "Beyond Fake News: A FIMI Briefing for Journalists",
    "url": "https://www.facebook.com/share/p/176Tt8hD5Z/",
    "date": "2025-09-23T12:00:00.000Z"
  },
  {
    "slug": "one-year-after-youth-protest-memory-civic-futures",
    "title": "One Year After: Youth, Protest Memory, and Civic Futures",
    "url": "https://www.facebook.com/activate.rights/posts/pfbid0cwRPnFQQT3iAdEcBw2pNVPKKtYETfs59gRZWhK3FxXRZNhM7sMJRHUJ74c13U9Srl",
    "date": "2025-09-20T12:00:00.000Z"
  },
  {
    "slug": "build4democracy-hackathon-2025",
    "title": "Build4Democracy Hackathon 2025",
    "url": "https://www.facebook.com/share/p/17edP1cjvy/",
    "date": "2025-09-17T12:00:00.000Z"
  },
  {
    "slug": "verify-resist-workshop",
    "title": "Verify & Resist workshop",
    "url": "https://www.facebook.com/share/p/1857Dyzadj/",
    "date": "2025-09-14T12:00:00.000Z"
  },
  {
    "slug": "archive-resist-conclave-coxs-bazar",
    "title": "Archive & Resist Conclave (Cox’s Bazar Edition)",
    "url": "https://www.facebook.com/share/p/1ER9UGG9ah/",
    "date": "2025-09-11T12:00:00.000Z"
  },
  {
    "slug": "archive-resist-conclave-brac-university",
    "title": "Archive & Resist Conclave (BRAC University)",
    "url": "https://www.facebook.com/share/p/17nyssz1br/",
    "date": "2025-09-08T12:00:00.000Z"
  }
]
